mondo/__init__.py
mondo/__main__.py
mondo/about.py
mondo/datetime_subset.py
mondo/export_csv.py
mondo/export_script.py
mondo/info_dialog.py
mondo/main.py
mondo/mondo_rc.py
mondo/preferences.py
mondo/psd_options.py
mondo/select_subchannels.py
mondo/select_synchronous.py
mondo/setting_viewer.py
mondo/ui_about.py
mondo/ui_datetime_subset.py
mondo/ui_info_dialog.py
mondo/ui_main.py
mondo/ui_preferences.py
mondo/ui_psd_options.py
mondo/ui_select_subchannels.py
mondo/ui_select_synchronous.py
mondo/ui_setting_viewer.py
mondo/version.py
mondo/analysis/__init__.py
mondo/analysis/csv.py
mondo/analysis/file.py
mondo/analysis/psd.py
mondo/analysis/spectrogram.py
mondo/analysis/time.py
mondo/analysis/util.py
mondo-2.1.0.dist-info/METADATA
mondo-2.1.0.dist-info/WHEEL
mondo-2.1.0.dist-info/entry_points.txt
mondo-2.1.0.dist-info/top_level.txt
mondo-2.1.0.dist-info/RECORD
