Metadata-Version: 2.1
Name: mondo
Version: 2.1.0
Summary: Application for analyzing recorded Asphodel sensor data
Home-page: https://bitbucket.org/suprocktech/mondo
Author: Suprock Technologies, LLC
Author-email: inquiries@suprocktech.com
License: UNKNOWN
Keywords: asphodel suprock apd
Platform: UNKNOWN
Classifier: Programming Language :: Python :: 3
Classifier: License :: OSI Approved :: ISC License (ISCL)
Classifier: Operating System :: OS Independent
Classifier: Topic :: System :: Hardware
Requires-Python: >=3.6
Requires-Dist: asphodel
Requires-Dist: hyperborea
Requires-Dist: matplotlib
Requires-Dist: numpy
Requires-Dist: PySide2
Requires-Dist: requests
Requires-Dist: scipy
